chaincash/__init__.py
chaincash/core/__init__.py
chaincash/core/blockchain_client.py
chaincash/core/constants.py
chaincash/core/models.py
chaincash/core/monitor.py
chaincash/core/transfer_service.py
chaincash/core/wallet_manager.py
chaincash/core/worker.py
chaincash/utils/__init__.py
chaincash/utils/exceptions.py
chaincash/utils/logger.py
chaincash-0.1.2.dist-info/licenses/LICENSE
tests/__init__.py
tests/test_blockchain_client.py
tests/test_transfer_service.py
tests/test_wallet_manager.py
chaincash-0.1.2.dist-info/METADATA
chaincash-0.1.2.dist-info/WHEEL
chaincash-0.1.2.dist-info/top_level.txt
chaincash-0.1.2.dist-info/RECORD
