Metadata-Version: 2.4
Name: chaincash
Version: 0.1.2
Summary: ChainCash - Crypto payments library for BEP20
Home-page: https://github.com/SaeedNoroozi/ChainCash
Author: Saeed Noroozi
Author-email: Saeed Noroozi <Noroozisaeed7@gmail.com>
License: MIT
Keywords: crypto,payments,bep20,web3,usdt,bnb
Requires-Python: >=3.9
License-File: LICENSE
Requires-Dist: web3>=6.0.0
Requires-Dist: loguru>=0.7.0
Requires-Dist: eth-utils>=5.3.0
Provides-Extra: dev
Requires-Dist: pytest>=7.0.0; extra == "dev"
Dynamic: author
Dynamic: home-page
Dynamic: license-file
Dynamic: requires-python
